turbosnake/__init__.py
turbosnake/_async.py
turbosnake/_components.py
turbosnake/_context.py
turbosnake/_functional_component.py
turbosnake/_hooks.py
turbosnake/_render_context.py
turbosnake/_slotted_component.py
turbosnake/_utils.py
turbosnake/_utils0.py
turbosnake/test_helpers/__init__.py
turbosnake/test_helpers/_selectors.py
turbosnake/test_helpers/_test_helpers.py
turbosnake/ttk/__init__.py
turbosnake/ttk/_adapters.py
turbosnake/ttk/_composite.py
turbosnake/ttk/_core.py
turbosnake/ttk/_layout.py
turbosnake/ttk/_menu.py
turbosnake/ttk/_style.py
turbosnake/ttk/_utils.py
turbosnake-1.24.434.dist-info/LICENCE
turbosnake-1.24.434.dist-info/METADATA
turbosnake-1.24.434.dist-info/WHEEL
turbosnake-1.24.434.dist-info/top_level.txt
turbosnake-1.24.434.dist-info/RECORD
