Metadata-Version: 2.1
Name: turbosnake
Version: 1.24.434
Summary: React.js-like framework with components for native user interfaces
Home-page: https://github.com/AlexeyBond/turbosnake
Author: Alexey Bondarenko
Author-email: alexey.bond.94.55+turbosnake@gmail.com
License: MIT
Keywords: ui,reactive,tkinter
Classifier: Development Status :: 4 - Beta
Classifier: Intended Audience :: Developers
Classifier: License :: OSI Approved :: MIT License
Classifier: Operating System :: Microsoft :: Windows
Classifier: Operating System :: Unix
Classifier: Operating System :: MacOS
Classifier: Programming Language :: Python :: 3.10
Classifier: Topic :: Software Development :: User Interfaces
License-File: LICENCE
